{
  "main": {
    "id": "e59733916b2e0a33",
    "type": "split",
    "children": [
      {
        "id": "f0e54927e178dca7",
        "type": "tabs",
        "dimension": 55.32994923857868,
        "children": [
          {
            "id": "c44f7d9e6739c8cd",
            "type": "leaf",
            "state": {
              "type": "markdown",
              "state": {
                "file": "Oracle Cloud/Oracle Cloud Infrastructure Foundation Certification Course/Oracle Cloud Infrastructure Foundation Certification Course.md",
                "mode": "source",
                "source": false
              },
              "icon": "lucide-file",
              "title": "Oracle Cloud Infrastructure Foundation Certification Course"
            }
          }
        ]
      },
      {
        "id": "4e2215f002c3e209",
        "type": "tabs",
        "dimension": 44.67005076142132,
        "children": [
          {
            "id": "826a651ada802598",
            "type": "leaf",
            "state": {
              "type": "markdown",
              "state": {
                "file": "README.md",
                "mode": "source",
                "source": false
              },
              "icon": "lucide-file",
              "title": "README"
            }
          }
        ]
      }
    ],
    "direction": "vertical"
  },
  "left": {
    "id": "6aa10c2b1faec4f9",
    "type": "split",
    "children": [
      {
        "id": "f23752b59e608467",
        "type": "tabs",
        "children": [
          {
            "id": "106b69fe72aa2a09",
            "type": "leaf",
            "state": {
              "type": "file-explorer",
              "state": {
                "sortOrder": "alphabetical",
                "autoReveal": false
              },
              "icon": "lucide-folder-closed",
              "title": "Files"
            }
          },
          {
            "id": "fa27db4a38921493",
            "type": "leaf",
            "state": {
              "type": "search",
              "state": {
                "query": "",
                "matchingCase": false,
                "explainSearch": false,
                "collapseAll": false,
                "extraContext": false,
                "sortOrder": "alphabetical"
              },
              "icon": "lucide-search",
              "title": "Search"
            }
          },
          {
            "id": "58a806606eb87bc8",
            "type": "leaf",
            "state": {
              "type": "bookmarks",
              "state": {},
              "icon": "lucide-bookmark",
              "title": "Bookmarks"
            }
          }
        ]
      }
    ],
    "direction": "horizontal",
    "width": 300
  },
  "right": {
    "id": "0d3195769606f594",
    "type": "split",
    "children": [
      {
        "id": "3e687d37fa9eca2a",
        "type": "tabs",
        "children": [
          {
            "id": "a1ed333b60b60683",
            "type": "leaf",
            "state": {
              "type": "backlink",
              "state": {
                "collapseAll": false,
                "extraContext": false,
                "sortOrder": "alphabetical",
                "showSearch": false,
                "searchQuery": "",
                "backlinkCollapsed": false,
                "unlinkedCollapsed": true
              },
              "icon": "links-coming-in",
              "title": "Backlinks"
            }
          },
          {
            "id": "59782381970103f9",
            "type": "leaf",
            "state": {
              "type": "outgoing-link",
              "state": {
                "linksCollapsed": false,
                "unlinkedCollapsed": true
              },
              "icon": "links-going-out",
              "title": "Outgoing links"
            }
          },
          {
            "id": "7759ae8f0bcff35f",
            "type": "leaf",
            "state": {
              "type": "tag",
              "state": {
                "sortOrder": "frequency",
                "useHierarchy": true,
                "showSearch": false,
                "searchQuery": ""
              },
              "icon": "lucide-tags",
              "title": "Tags"
            }
          },
          {
            "id": "8598fe0c700261eb",
            "type": "leaf",
            "state": {
              "type": "outline",
              "state": {
                "followCursor": false,
                "showSearch": false,
                "searchQuery": ""
              },
              "icon": "lucide-list",
              "title": "Outline"
            }
          },
          {
            "id": "507b7fe7dbbb7e26",
            "type": "leaf",
            "state": {
              "type": "calendar",
              "state": {},
              "icon": "calendar-with-checkmark",
              "title": "Calendar"
            }
          }
        ]
      }
    ],
    "direction": "horizontal",
    "width": 300,
    "collapsed": true
  },
  "left-ribbon": {
    "hiddenItems": {
      "switcher:Open quick switcher": false,
      "graph:Open graph view": false,
      "canvas:Create new canvas": false,
      "daily-notes:Open today's daily note": false,
      "templates:Insert template": false,
      "command-palette:Open command palette": false
    }
  },
  "active": "106b69fe72aa2a09",
  "lastOpenFiles": [
    "Estudar.md",
    "Oracle Cloud/Oracle Cloud Infrastructure Foundation Certification Course/Oracle Cloud Infrastructure Foundation Certification Course.md",
    "Oracle Cloud/Oracle Cloud Infrastructure Foundation Certification Course/SkillCheck/3/assets/5.png",
    "Oracle Cloud/Oracle Cloud Infrastructure Foundation Certification Course/SkillCheck/3/assets/3.png",
    "Oracle Cloud/Oracle Cloud Infrastructure Foundation Certification Course/SkillCheck/3/assets/4.png",
    "Oracle Cloud/Oracle Cloud Infrastructure Foundation Certification Course/SkillCheck/3/assets/2.png",
    "Oracle Cloud/Oracle Cloud Infrastructure Foundation Certification Course/SkillCheck/3/assets/1.png",
    "Oracle Cloud/Oracle Cloud Infrastructure Foundation Certification Course/SkillCheck/3/Network.md",
    "Oracle Cloud/Oracle Cloud Infrastructure Foundation Certification Course/SkillCheck/3/assets",
    "Oracle Cloud/Oracle Cloud Infrastructure Foundation Certification Course/SkillCheck/3",
    "Oracle Cloud/Oracle Cloud Infrastructure Foundation Certification Course/SkillCheck/2/assets/foto4.png",
    "Oracle Cloud/Oracle Cloud Infrastructure Foundation Certification Course/SkillCheck/2/assets/foto3.png",
    "Oracle Cloud/Oracle Cloud Infrastructure Foundation Certification Course/SkillCheck/2/assets/foto5.png",
    "Oracle Cloud/Oracle Cloud Infrastructure Foundation Certification Course/SkillCheck/2/assets/foto1.png",
    "Oracle Cloud/Oracle Cloud Infrastructure Foundation Certification Course/SkillCheck/2/assets/foto2.png",
    "Oracle Cloud/Oracle Cloud Infrastructure Foundation Certification Course/SkillCheck/2/Identity and Access Management.md",
    "Oracle Cloud/Oracle Cloud Infrastructure Foundation Certification Course/SkillCheck/2/assets",
    "Oracle Cloud/Oracle Cloud Infrastructure Foundation Certification Course/SkillCheck/2",
    "Oracle Cloud/Oracle Cloud Infrastructure Foundation Certification Course/SkillCheck/1/OCI Introduction.md",
    "Oracle Cloud/Oracle Cloud Infrastructure Foundation Certification Course/SkillCheck/1/assets",
    "Oracle Cloud/Oracle Cloud Infrastructure Foundation Certification Course/SkillCheck/1",
    "Oracle Cloud/Oracle Cloud Infrastructure Foundation Certification Course/assets",
    "README.md",
    "Oracle Cloud/Oracle Cloud Infrastructure Foundation Certification Course",
    "Oracle Cloud",
    "Obsidian/Annotations/Obsidian & Git.md",
    "Oracle Cloud/Oracle Cloud Infrastructure Foundation Certification Course/SkillCheck",
    "Obsidian/Annotations/Daily note.md",
    "Obsidian/Annotations/Configurando Obsidian.md",
    "Obsidian/Annotations/daily/2025-04-29.md",
    "Estudos/README.md",
    "Estudos/Obsidian/Annotations/daily/2025-04-29.md",
    "Estudos/Obsidian/Annotations/Daily note.md",
    "Estudos/Obsidian/Annotations/Obsidian & Git.md",
    "Estudos/Obsidian/Annotations/Configurando Obsidian.md",
    "Estudos/Estudar.md",
    "Welcome.md"
  ]
}